alice/__init__.py
alice/cli.py
alice/server.py
alice-0.0.1.dist-info/METADATA
alice-0.0.1.dist-info/WHEEL
alice-0.0.1.dist-info/entry_points.txt
alice-0.0.1.dist-info/top_level.txt
alice-0.0.1.dist-info/RECORD
