Metadata-Version: 2.1
Name: alice
Version: 0.0.1
Summary: A Simple and Scalable Logging Utility With a Beautiful Visualization Dashboard
Home-page: https://github.com/geyang/alice
Author: Ge Yang
Author-email: ge.ike.yang@gmail.com
License: UNKNOWN
Keywords: alice,visualization,logging,debug,debugging
Platform: UNKNOWN
Classifier: Development Status :: 4 - Beta
Classifier: Intended Audience :: Science/Research
Classifier: Programming Language :: Python :: 3
